{
  "agent_id": "08879b11-3585-4919-89c0-a0725f17039b",
  "generated_at": "2025-12-02T08:52:11.084317",
  "basic_info": {
    "title": "Amazon Product Search",
    "author": "createAny",
    "description": "The Amazon product scraper is a powerful, reliable data extraction tool that automatically collects accurate product data for e-commerce insights.",
    "short_description": "Scrapes Amazon product data by keyword, domain, and pages.",
    "category": "AI Agent",
    "is_active": true,
    "published_at": "2025-10-13T18:19:42.979000",
    "last_seen": null,
    "profile_url": "https://mulerun.com/workspace/@createAny/amazon-product-search",
    "days_since_published": 49
  },
  "performance_metrics": {
    "views": 0,
    "runs": 0,
    "saves": 0,
    "days_tracked": 49,
    "price": 10.0,
    "engagement_rate": 0,
    "avg_runs_per_day": 0.0,
    "avg_views_per_day": 0.0
  },
  "historical_trends": {
    "has_data": true,
    "data_points": 16,
    "first_recorded": "2025-11-19T15:39:36.345282",
    "last_recorded": "2025-12-02T16:52:00.461129",
    "time_series": {
      "dates": [
        "2025-11-19T15:39:36.345282",
        "2025-11-19T16:22:32.765134",
        "2025-11-21T14:09:56.591648",
        "2025-11-23T13:27:48.290198",
        "2025-11-23T14:00:32.439099",
        "2025-11-23T19:55:14.744404",
        "2025-11-23T20:03:58.312245",
        "2025-11-24T09:54:21.691735",
        "2025-11-25T08:00:22.881701",
        "2025-11-26T08:00:32.046352",
        "2025-11-27T08:00:22.157746",
        "2025-11-27T16:15:10.235580",
        "2025-11-28T08:00:25.835604",
        "2025-11-30T15:58:50.561480",
        "2025-12-01T08:00:25.084545",
        "2025-12-02T16:52:00.461129"
      ],
      "views": [
        135,
        136,
        143,
        144,
        144,
        144,
        144,
        146,
        147,
        147,
        147,
        147,
        151,
        155,
        155,
        0
      ],
      "runs": [
        2,
        2,
        0,
        0,
        0,
        0,
        0,
        0,
        0,
        0,
        0,
        0,
        0,
        1,
        1,
        0
      ],
      "saves": [
        0,
        0,
        0,
        0,
        0,
        0,
        0,
        0,
        0,
        0,
        0,
        0,
        0,
        0,
        0,
        0
      ]
    }
  },
  "growth_analysis": {
    "has_data": true,
    "days_tracked": 13,
    "total_growth": {
      "views": -135,
      "runs": -2,
      "saves": 0
    },
    "daily_average_growth": {
      "views": -10.38,
      "runs": -0.15,
      "saves": 0.0
    },
    "percentage_growth": {
      "views": -100.0,
      "runs": -100.0,
      "saves": 0
    }
  },
  "change_history": {
    "total_changes": 0,
    "changes": []
  },
  "market_position": {
    "total_active_agents": 205,
    "views_rank": 1,
    "runs_rank": 1,
    "views_percentile": 99.5,
    "runs_percentile": 99.5,
    "category": "AI Agent",
    "category_agent_count": 205,
    "vs_average": {
      "views": 0,
      "runs": 0,
      "saves": 0
    }
  },
  "insights": [
    {
      "type": "warning",
      "title": "Low Engagement Rate",
      "description": "The engagement rate is 0.0%, which may indicate the agent description or value proposition could be improved."
    },
    {
      "type": "positive",
      "title": "Top Performer",
      "description": "This agent ranks in the top 0% by views, placing it among the most popular agents."
    }
  ]
}