{
  "agent_id": "10aa0000-d27e-49f0-9ee9-0ad7d99f57b3",
  "generated_at": "2025-11-27T00:00:34.930304",
  "basic_info": {
    "title": "AI  Backgrounds",
    "author": "PicCopilot",
    "description": "Turn product photos into stunning visuals with AI background generator free. Automatic isolation with professional scenes to boost e-commerce sales in seconds.",
    "short_description": "Generate tailored AI backgrounds for e-commerce product photos.",
    "category": "AI Agent",
    "is_active": true,
    "published_at": "2025-11-11T19:33:20.689000",
    "last_seen": null,
    "profile_url": "https://mulerun.com/workspace/@PicCopilot/ai-backgrounds",
    "days_since_published": 15
  },
  "performance_metrics": {
    "views": 288,
    "runs": 602,
    "saves": 0,
    "days_tracked": 15,
    "price": 0.0,
    "engagement_rate": 209.03,
    "avg_runs_per_day": 40.13,
    "avg_views_per_day": 19.2
  },
  "historical_trends": {
    "has_data": true,
    "data_points": 11,
    "first_recorded": "2025-11-19T15:39:36.345282",
    "last_recorded": "2025-11-27T08:00:22.157746",
    "time_series": {
      "dates": [
        "2025-11-19T15:39:36.345282",
        "2025-11-19T16:22:32.765134",
        "2025-11-21T14:09:56.591648",
        "2025-11-23T13:27:48.290198",
        "2025-11-23T14:00:32.439099",
        "2025-11-23T19:55:14.744404",
        "2025-11-23T20:03:58.312245",
        "2025-11-24T09:54:21.691735",
        "2025-11-25T08:00:22.881701",
        "2025-11-26T08:00:32.046352",
        "2025-11-27T08:00:22.157746"
      ],
      "views": [
        231,
        231,
        245,
        252,
        252,
        252,
        252,
        254,
        263,
        278,
        288
      ],
      "runs": [
        55,
        55,
        321,
        515,
        515,
        568,
        571,
        572,
        655,
        677,
        602
      ],
      "saves": [
        0,
        0,
        0,
        0,
        0,
        0,
        0,
        0,
        0,
        0,
        0
      ]
    }
  },
  "growth_analysis": {
    "has_data": true,
    "days_tracked": 7,
    "total_growth": {
      "views": 57,
      "runs": 547,
      "saves": 0
    },
    "daily_average_growth": {
      "views": 8.14,
      "runs": 78.14,
      "saves": 0.0
    },
    "percentage_growth": {
      "views": 24.68,
      "runs": 994.55,
      "saves": 0
    }
  },
  "change_history": {
    "total_changes": 0,
    "changes": []
  },
  "market_position": {
    "total_active_agents": 204,
    "views_rank": 98,
    "runs_rank": 7,
    "views_percentile": 52.0,
    "runs_percentile": 96.6,
    "category": "AI Agent",
    "category_agent_count": 204,
    "vs_average": {
      "views": -59.5,
      "runs": 1032.7,
      "saves": 0
    }
  },
  "insights": [
    {
      "type": "positive",
      "title": "High Engagement Rate",
      "description": "This agent has an excellent 209.0% engagement rate (runs/views), significantly above average."
    },
    {
      "type": "positive",
      "title": "Active User Base",
      "description": "Runs increased by 547, indicating growing adoption and active usage."
    }
  ]
}