{
  "agent_id": "a6b8beaa-a431-4ae4-9f51-044fbdcd64f0",
  "generated_at": "2025-12-17T08:24:45.852655",
  "basic_info": {
    "title": "Festival Purikura",
    "author": "Norsizu",
    "description": "Create cute 3x3 festival Purikura collages for friends and couples.",
    "short_description": "Create cute 3x3 festival Purikura photo collages from portraits.",
    "category": "AI Agent",
    "is_active": true,
    "published_at": "2025-12-09T19:56:57.349000",
    "last_seen": null,
    "profile_url": "https://mulerun.com/workspace/@Norsizu/festival-purikura",
    "days_since_published": 7
  },
  "ranking_metrics": {
    "current_position": {
      "views_rank": 219,
      "runs_rank": 125,
      "likes_rank": 1,
      "total_agents": 245,
      "views_percentile": 10.6,
      "runs_percentile": 49.0,
      "likes_percentile": 99.6
    },
    "tier": "Elite",
    "tier_class": "elite",
    "days_tracked": 10,
    "price": 75.0
  },
  "ranking_trends": {
    "has_data": true,
    "days_tracked": 5,
    "last_7_days": {
      "views_rank_change": null,
      "runs_rank_change": null,
      "likes_rank_change": null
    },
    "last_30_days": {
      "views_rank_change": null,
      "runs_rank_change": null,
      "likes_rank_change": null
    },
    "all_time": {
      "best_views_rank": 219,
      "best_runs_rank": 125,
      "best_likes_rank": 1,
      "days_in_top_10": 0,
      "first_rank": null,
      "current_rank": 219
    }
  },
  "historical_rankings": {
    "has_data": true,
    "data_points": 10,
    "first_recorded": "2025-12-12T08:00:25.373075",
    "last_recorded": "2025-12-17T16:24:33.627352",
    "time_series": {
      "dates": [
        "2025-12-12T08:00:25.373075",
        "2025-12-13T08:00:26.854786",
        "2025-12-14T08:00:33.104463",
        "2025-12-15T08:00:24.739668",
        "2025-12-16T19:09:41.063612",
        "2025-12-16T21:38:18.856537",
        "2025-12-17T08:00:57.764340",
        "2025-12-17T11:30:34.217578",
        "2025-12-17T13:39:15.961442",
        "2025-12-17T16:24:33.627352"
      ],
      "views_rank": [
        null,
        null,
        null,
        null,
        null,
        219,
        219,
        219,
        219,
        219
      ],
      "runs_rank": [
        null,
        null,
        null,
        null,
        null,
        125,
        125,
        125,
        125,
        125
      ],
      "likes_rank": [
        null,
        null,
        null,
        null,
        null,
        232,
        232,
        232,
        232,
        1
      ]
    }
  },
  "change_history": {
    "total_changes": 1,
    "changes": [
      {
        "date": "2025-12-12T00:00:26.511875",
        "type": "new",
        "description": "New agent published: Festival Purikura",
        "severity": "medium"
      }
    ]
  },
  "insights": [
    {
      "type": "positive",
      "title": "Elite Performance",
      "description": "Ranked #1 - This agent is in the Elite tier (Top 5%), consistently performing among the best agents on the platform."
    }
  ]
}